<vector xmlns:aapt="http://schemas.android.com/aapt" xmlns:android="http://schemas.android.com/apk/res/android" android:height="48dp" android:viewportHeight="95" android:viewportWidth="95" android:width="48dp">
      
    <group>
            
        <clip-path android:pathData="M0,0h95v95h-95z"/>
            
        <path android:pathData="M41,0L54,0A41,41 0,0 1,95 41L95,54A41,41 0,0 1,54 95L41,95A41,41 0,0 1,0 54L0,41A41,41 0,0 1,41 0z">
                  
            <aapt:attr name="android:fillColor">
                        
                <gradient android:endX="47.5" android:endY="95" android:startX="47.5" android:startY="0" android:type="linear">
                              
                    <item android:color="#99FFD400" android:offset="0"/>
                              
                    <item android:color="#FFFF6600" android:offset="1"/>
                            
                </gradient>
                      
            </aapt:attr>
                
        </path>
            
        <path android:fillAlpha="0.2" android:pathData="M74.5,66.548L74.5,46.638L75.385,46.638C77.38,46.638 79,45.038 79,43.065L79,42.545C79,41.07 78.26,39.69 77.026,38.862L57.526,25.769C56,24.744 53.997,24.744 52.471,25.769L32.971,38.862C31.738,39.691 31,41.07 31,42.545L31,43.062C31,45.038 32.62,46.638 34.615,46.638L35.5,46.638L35.5,66.548C35.5,69.007 37.515,71 40,71L70,71C72.485,71 74.5,69.007 74.5,66.548ZM54.538,42.777C57.912,42.771 61.005,44.632 62.552,47.598C64.099,50.564 63.839,54.136 61.879,56.853L65.137,60.073C65.721,60.651 65.721,61.587 65.137,62.165C64.553,62.743 63.606,62.743 63.022,62.165L59.761,58.939C54.794,62.428 47.831,60.13 45.977,54.39C44.123,48.649 48.449,42.783 54.541,42.777L54.538,42.777ZM54.538,45.744C56.957,45.755 59.133,47.201 60.057,49.412C60.982,51.623 60.473,54.167 58.768,55.864C56.426,58.176 52.635,58.176 50.293,55.864C47.957,53.548 47.957,49.797 50.293,47.481C51.419,46.368 52.946,45.743 54.538,45.744Z" android:strokeAlpha="0.2">
                  
            <aapt:attr name="android:fillColor">
                        
                <gradient android:endX="55" android:endY="71" android:startX="55" android:startY="24.744" android:type="linear">
                              
                    <item android:color="#FFFFFFFF" android:offset="0.7"/>
                              
                    <item android:color="#00FFFFFF" android:offset="1"/>
                            
                </gradient>
                      
            </aapt:attr>
                
        </path>
            
        <path android:fillColor="#FFFFFF" android:pathData="M66.5,66.548L66.5,46.638L67.385,46.638C69.38,46.638 71,45.038 71,43.065L71,42.545C71,41.07 70.26,39.69 69.026,38.862L49.526,25.769C48,24.744 45.997,24.744 44.471,25.769L24.971,38.862C23.738,39.691 23,41.07 23,42.545L23,43.062C23,45.038 24.62,46.638 26.615,46.638L27.5,46.638L27.5,66.548C27.5,69.007 29.515,71 32,71L62,71C64.485,71 66.5,69.007 66.5,66.548ZM46.538,42.777C49.912,42.771 53.005,44.632 54.552,47.598C56.099,50.564 55.839,54.136 53.879,56.853L57.137,60.073C57.721,60.651 57.721,61.587 57.137,62.165C56.553,62.743 55.606,62.743 55.022,62.165L51.761,58.939C46.794,62.428 39.831,60.13 37.977,54.39C36.123,48.649 40.449,42.783 46.541,42.777L46.538,42.777ZM46.538,45.744C48.957,45.755 51.133,47.201 52.057,49.412C52.982,51.623 52.473,54.167 50.768,55.864C48.426,58.176 44.635,58.176 42.293,55.864C39.957,53.548 39.957,49.797 42.293,47.481C43.419,46.368 44.946,45.743 46.538,45.744Z"/>
          
    </group>
    
</vector>
